[
  {
    "index": 127,
    "id": "9",
    "version": "14.3.1",
    "officialVersion": "14.4.1",
    "pickCount": 11816,
    "winRate": "49.54%",
    "timestamp": 1709583153942,
    "alias": "Fiddlesticks",
    "name": "Fiddlesticks",
    "position": "jungle",
    "skills": [
      "W",
      "Q",
      "E"
    ],
    "spells": null,
    "itemBuilds": [
      {
        "title": "[u.gg] Fiddlesticks @ jungle, 14.4.1",
        "associatedMaps": [
          11,
          12
        ],
        "associatedChampions": [
          9
        ],
        "blocks": [
          {
            "type": "Starting Items, pick count 5879, win 49.72%, W \u003e Q \u003e E",
            "items": [
              {
                "id": "1102",
                "count": 1
              }
            ]
          },
          {
            "type": "Mythic \u0026 Core Items, pick count 659, win 52.81%, W \u003e Q \u003e E",
            "items": [
              {
                "id": "3020",
                "count": 1
              },
              {
                "id": "3118",
                "count": 1
              },
              {
                "id": "3152",
                "count": 1
              }
            ]
          },
          {
            "type": "Fourth Item Options, W \u003e Q \u003e E",
            "items": [
              {
                "id": "3157",
                "count": 1
              },
              {
                "id": "3041",
                "count": 1
              }
            ]
          },
          {
            "type": "Fifth Item Options, W \u003e Q \u003e E",
            "items": [
              {
                "id": "3137",
                "count": 1
              },
              {
                "id": "3157",
                "count": 1
              },
              {
                "id": "4645",
                "count": 1
              }
            ]
          },
          {
            "type": "Sixth Item Options, W \u003e Q \u003e E",
            "items": [
              {
                "id": "3089",
                "count": 1
              },
              {
                "id": "3102",
                "count": 1
              },
              {
                "id": "6653",
                "count": 1
              }
            ]
          }
        ],
        "map": "any",
        "mode": "any",
        "preferredItemSlots": null,
        "sortrank": 1,
        "startedFrom": "blank",
        "type": "custom"
      }
    ],
    "runes": [
      {
        "alias": "Fiddlesticks",
        "name": "[u.gg] Fiddlesticks @ jungle, win 51.82%, pick 1015",
        "position": "jungle",
        "pickCount": 1015,
        "winRate": "51.82%",
        "primaryStyleId": 8300,
        "subStyleId": 8100,
        "selectedPerkIds": [
          8369,
          8106,
          8143,
          8306,
          8321,
          8347,
          5008,
          5008,
          5011
        ],
        "score": 0,
        "type": ""
      }
    ]
  },
  {
    "index": 127,
    "id": "9",
    "version": "14.3.1",
    "officialVersion": "14.4.1",
    "pickCount": 2544,
    "winRate": "49.49%",
    "timestamp": 1709583153942,
    "alias": "Fiddlesticks",
    "name": "Fiddlesticks",
    "position": "supp",
    "skills": [
      "W",
      "Q",
      "E"
    ],
    "spells": null,
    "itemBuilds": [
      {
        "title": "[u.gg] Fiddlesticks @ supp, 14.4.1",
        "associatedMaps": [
          11,
          12
        ],
        "associatedChampions": [
          9
        ],
        "blocks": [
          {
            "type": "Starting Items, pick count 46, win 65.22%, W \u003e Q \u003e E",
            "items": [
              {
                "id": "2055",
                "count": 1
              },
              {
                "id": "3865",
                "count": 1
              }
            ]
          },
          {
            "type": "Mythic \u0026 Core Items, pick count 114, win 58.77%, W \u003e Q \u003e E",
            "items": [
              {
                "id": "3876",
                "count": 1
              },
              {
                "id": "3009",
                "count": 1
              },
              {
                "id": "3110",
                "count": 1
              }
            ]
          },
          {
            "type": "Fourth Item Options, W \u003e Q \u003e E",
            "items": [
              {
                "id": "3157",
                "count": 1
              },
              {
                "id": "3118",
                "count": 1
              }
            ]
          },
          {
            "type": "Fifth Item Options, W \u003e Q \u003e E",
            "items": [
              {
                "id": "6653",
                "count": 1
              },
              {
                "id": "4646",
                "count": 1
              },
              {
                "id": "3157",
                "count": 1
              }
            ]
          },
          {
            "type": "Sixth Item Options, W \u003e Q \u003e E",
            "items": [
              {
                "id": "4645",
                "count": 1
              },
              {
                "id": "3137",
                "count": 1
              },
              {
                "id": "4643",
                "count": 1
              }
            ]
          }
        ],
        "map": "any",
        "mode": "any",
        "preferredItemSlots": null,
        "sortrank": 1,
        "startedFrom": "blank",
        "type": "custom"
      }
    ],
    "runes": [
      {
        "alias": "Fiddlesticks",
        "name": "[u.gg] Fiddlesticks @ supp, win 69.23%, pick 39",
        "position": "supp",
        "pickCount": 39,
        "winRate": "69.23%",
        "primaryStyleId": 8200,
        "subStyleId": 8100,
        "selectedPerkIds": [
          8229,
          8106,
          8136,
          8226,
          8233,
          8237,
          5007,
          5008,
          5013
        ],
        "score": 0,
        "type": ""
      }
    ]
  },
  {
    "index": 127,
    "id": "9",
    "version": "14.3.1",
    "officialVersion": "14.4.1",
    "pickCount": 833,
    "winRate": "51.98%",
    "timestamp": 1709583153942,
    "alias": "Fiddlesticks",
    "name": "Fiddlesticks",
    "position": "top",
    "skills": [
      "W",
      "Q",
      "E"
    ],
    "spells": null,
    "itemBuilds": [
      {
        "title": "[u.gg] Fiddlesticks @ top, 14.4.1",
        "associatedMaps": [
          11,
          12
        ],
        "associatedChampions": [
          9
        ],
        "blocks": [
          {
            "type": "Starting Items, pick count 761, win 52.17%, W \u003e Q \u003e E",
            "items": [
              {
                "id": "1056",
                "count": 1
              },
              {
                "id": "2003",
                "count": 1
              },
              {
                "id": "2003",
                "count": 1
              }
            ]
          },
          {
            "type": "Mythic \u0026 Core Items, pick count 20, win 85.00%, W \u003e Q \u003e E",
            "items": [
              {
                "id": "3020",
                "count": 1
              },
              {
                "id": "3118",
                "count": 1
              },
              {
                "id": "6653",
                "count": 1
              }
            ]
          },
          {
            "type": "Fourth Item Options, W \u003e Q \u003e E",
            "items": [
              {
                "id": "3157",
                "count": 1
              },
              {
                "id": "3089",
                "count": 1
              }
            ]
          },
          {
            "type": "Fifth Item Options, W \u003e Q \u003e E",
            "items": [
              {
                "id": "3165",
                "count": 1
              },
              {
                "id": "4645",
                "count": 1
              },
              {
                "id": "3137",
                "count": 1
              }
            ]
          },
          {
            "type": "Sixth Item Options, W \u003e Q \u003e E",
            "items": [
              {
                "id": "4646",
                "count": 1
              },
              {
                "id": "4629",
                "count": 1
              },
              {
                "id": "3157",
                "count": 1
              }
            ]
          }
        ],
        "map": "any",
        "mode": "any",
        "preferredItemSlots": null,
        "sortrank": 1,
        "startedFrom": "blank",
        "type": "custom"
      }
    ],
    "runes": [
      {
        "alias": "Fiddlesticks",
        "name": "[u.gg] Fiddlesticks @ top, win 70.37%, pick 27",
        "position": "top",
        "pickCount": 27,
        "winRate": "70.37%",
        "primaryStyleId": 8200,
        "subStyleId": 8400,
        "selectedPerkIds": [
          8229,
          8210,
          8226,
          8237,
          8451,
          8473,
          5007,
          5001,
          5011
        ],
        "score": 0,
        "type": ""
      }
    ]
  },
  {
    "index": 127,
    "id": "9",
    "version": "14.3.1",
    "officialVersion": "14.4.1",
    "pickCount": 830,
    "winRate": "52.41%",
    "timestamp": 1709583153942,
    "alias": "Fiddlesticks",
    "name": "Fiddlesticks",
    "position": "mid",
    "skills": [
      "W",
      "Q",
      "E"
    ],
    "spells": null,
    "itemBuilds": [
      {
        "title": "[u.gg] Fiddlesticks @ mid, 14.4.1",
        "associatedMaps": [
          11,
          12
        ],
        "associatedChampions": [
          9
        ],
        "blocks": [
          {
            "type": "Starting Items, pick count 797, win 52.70%, W \u003e Q \u003e E",
            "items": [
              {
                "id": "1056",
                "count": 1
              },
              {
                "id": "2003",
                "count": 1
              },
              {
                "id": "2003",
                "count": 1
              }
            ]
          },
          {
            "type": "Mythic \u0026 Core Items, pick count 65, win 60.00%, W \u003e Q \u003e E",
            "items": [
              {
                "id": "3020",
                "count": 1
              },
              {
                "id": "3118",
                "count": 1
              },
              {
                "id": "6653",
                "count": 1
              }
            ]
          },
          {
            "type": "Fourth Item Options, W \u003e Q \u003e E",
            "items": [
              {
                "id": "3102",
                "count": 1
              },
              {
                "id": "4645",
                "count": 1
              }
            ]
          },
          {
            "type": "Fifth Item Options, W \u003e Q \u003e E",
            "items": [
              {
                "id": "3157",
                "count": 1
              },
              {
                "id": "3137",
                "count": 1
              },
              {
                "id": "3089",
                "count": 1
              }
            ]
          },
          {
            "type": "Sixth Item Options, W \u003e Q \u003e E",
            "items": [
              {
                "id": "3165",
                "count": 1
              },
              {
                "id": "3152",
                "count": 1
              }
            ]
          }
        ],
        "map": "any",
        "mode": "any",
        "preferredItemSlots": null,
        "sortrank": 1,
        "startedFrom": "blank",
        "type": "custom"
      }
    ],
    "runes": [
      {
        "alias": "Fiddlesticks",
        "name": "[u.gg] Fiddlesticks @ mid, win 58.54%, pick 82",
        "position": "mid",
        "pickCount": 82,
        "winRate": "58.54%",
        "primaryStyleId": 8200,
        "subStyleId": 8100,
        "selectedPerkIds": [
          8229,
          8106,
          8126,
          8210,
          8226,
          8237,
          5008,
          5008,
          5011
        ],
        "score": 0,
        "type": ""
      }
    ]
  },
  {
    "index": 127,
    "id": "9",
    "version": "14.3.1",
    "officialVersion": "14.4.1",
    "pickCount": 17,
    "winRate": "35.29%",
    "timestamp": 1709583153942,
    "alias": "Fiddlesticks",
    "name": "Fiddlesticks",
    "position": "adc",
    "skills": [
      "Q",
      "W",
      "E"
    ],
    "spells": null,
    "itemBuilds": [
      {
        "title": "[u.gg] Fiddlesticks @ adc, 14.4.1",
        "associatedMaps": [
          11,
          12
        ],
        "associatedChampions": [
          9
        ],
        "blocks": [
          {
            "type": "Starting Items, pick count 1, win 100.00%, Q \u003e W \u003e E",
            "items": [
              {
                "id": "2003",
                "count": 1
              },
              {
                "id": "2003",
                "count": 1
              },
              {
                "id": "3865",
                "count": 1
              }
            ]
          },
          {
            "type": "Mythic \u0026 Core Items, pick count 1, win 100.00%, Q \u003e W \u003e E",
            "items": [
              {
                "id": "3871",
                "count": 1
              },
              {
                "id": "3158",
                "count": 1
              },
              {
                "id": "6653",
                "count": 1
              }
            ]
          },
          {
            "type": "Fourth Item Options, Q \u003e W \u003e E",
            "items": [
              {
                "id": "3157",
                "count": 1
              },
              {
                "id": "3135",
                "count": 1
              }
            ]
          },
          {
            "type": "Fifth Item Options, Q \u003e W \u003e E",
            "items": null
          },
          {
            "type": "Sixth Item Options, Q \u003e W \u003e E",
            "items": null
          }
        ],
        "map": "any",
        "mode": "any",
        "preferredItemSlots": null,
        "sortrank": 1,
        "startedFrom": "blank",
        "type": "custom"
      }
    ],
    "runes": [
      {
        "alias": "Fiddlesticks",
        "name": "[u.gg] Fiddlesticks @ adc, win 100.00%, pick 1",
        "position": "adc",
        "pickCount": 1,
        "winRate": "100.00%",
        "primaryStyleId": 8100,
        "subStyleId": 8200,
        "selectedPerkIds": [
          8124,
          8105,
          8136,
          8143,
          8232,
          8234,
          5008,
          5001,
          5001
        ],
        "score": 0,
        "type": ""
      }
    ]
  }
]