[
  {
    "index": 109,
    "id": "950",
    "version": "14.5.1",
    "officialVersion": "14.5.1",
    "pickCount": 490,
    "winRate": "51.43%",
    "timestamp": 1709755984766,
    "alias": "Naafiri",
    "name": "Naafiri",
    "position": "mid",
    "skills": [
      "Q",
      "E",
      "W"
    ],
    "spells": null,
    "itemBuilds": [
      {
        "title": "[u.gg] Naafiri @ mid, 14.5.1",
        "associatedMaps": [
          11,
          12
        ],
        "associatedChampions": [
          950
        ],
        "blocks": [
          {
            "type": "Starting Items, pick count 205, win 54.15%, Q \u003e E \u003e W",
            "items": [
              {
                "id": "1036",
                "count": 1
              },
              {
                "id": "2031",
                "count": 1
              }
            ]
          },
          {
            "type": "Mythic \u0026 Core Items, pick count 117, win 58.12%, Q \u003e E \u003e W",
            "items": [
              {
                "id": "6692",
                "count": 1
              },
              {
                "id": "3158",
                "count": 1
              },
              {
                "id": "6698",
                "count": 1
              }
            ]
          },
          {
            "type": "Fourth Item Options, Q \u003e E \u003e W",
            "items": [
              {
                "id": "6694",
                "count": 1
              },
              {
                "id": "6701",
                "count": 1
              }
            ]
          },
          {
            "type": "Fifth Item Options, Q \u003e E \u003e W",
            "items": [
              {
                "id": "3814",
                "count": 1
              },
              {
                "id": "6696",
                "count": 1
              },
              {
                "id": "6701",
                "count": 1
              }
            ]
          },
          {
            "type": "Sixth Item Options, Q \u003e E \u003e W",
            "items": [
              {
                "id": "3026",
                "count": 1
              },
              {
                "id": "6695",
                "count": 1
              },
              {
                "id": "3814",
                "count": 1
              }
            ]
          }
        ],
        "map": "any",
        "mode": "any",
        "preferredItemSlots": null,
        "sortrank": 1,
        "startedFrom": "blank",
        "type": "custom"
      }
    ],
    "runes": [
      {
        "alias": "Naafiri",
        "name": "[u.gg] Naafiri @ mid, win 65.12%, pick 43",
        "position": "mid",
        "pickCount": 43,
        "winRate": "65.12%",
        "primaryStyleId": 8300,
        "subStyleId": 8200,
        "selectedPerkIds": [
          8369,
          8210,
          8236,
          8304,
          8345,
          8347,
          5008,
          5008,
          5001
        ],
        "score": 0,
        "type": ""
      }
    ]
  },
  {
    "index": 109,
    "id": "950",
    "version": "14.5.1",
    "officialVersion": "14.5.1",
    "pickCount": 82,
    "winRate": "47.56%",
    "timestamp": 1709755984766,
    "alias": "Naafiri",
    "name": "Naafiri",
    "position": "top",
    "skills": [
      "Q",
      "E",
      "W"
    ],
    "spells": null,
    "itemBuilds": [
      {
        "title": "[u.gg] Naafiri @ top, 14.5.1",
        "associatedMaps": [
          11,
          12
        ],
        "associatedChampions": [
          950
        ],
        "blocks": [
          {
            "type": "Starting Items, pick count 1, win 100.00%, Q \u003e E \u003e W",
            "items": [
              {
                "id": "1036",
                "count": 1
              },
              {
                "id": "1055",
                "count": 1
              },
              {
                "id": "2003",
                "count": 1
              }
            ]
          },
          {
            "type": "Mythic \u0026 Core Items, pick count 3, win 100.00%, Q \u003e E \u003e W",
            "items": [
              {
                "id": "6692",
                "count": 1
              },
              {
                "id": "6698",
                "count": 1
              },
              {
                "id": "3814",
                "count": 1
              }
            ]
          },
          {
            "type": "Fourth Item Options, Q \u003e E \u003e W",
            "items": [
              {
                "id": "6701",
                "count": 1
              },
              {
                "id": "3156",
                "count": 1
              }
            ]
          },
          {
            "type": "Fifth Item Options, Q \u003e E \u003e W",
            "items": [
              {
                "id": "6609",
                "count": 1
              },
              {
                "id": "6701",
                "count": 1
              },
              {
                "id": "6694",
                "count": 1
              }
            ]
          },
          {
            "type": "Sixth Item Options, Q \u003e E \u003e W",
            "items": [
              {
                "id": "6695",
                "count": 1
              },
              {
                "id": "6694",
                "count": 1
              },
              {
                "id": "6676",
                "count": 1
              }
            ]
          }
        ],
        "map": "any",
        "mode": "any",
        "preferredItemSlots": null,
        "sortrank": 1,
        "startedFrom": "blank",
        "type": "custom"
      }
    ],
    "runes": [
      {
        "alias": "Naafiri",
        "name": "[u.gg] Naafiri @ top, win 66.67%, pick 9",
        "position": "top",
        "pickCount": 9,
        "winRate": "66.67%",
        "primaryStyleId": 8300,
        "subStyleId": 8100,
        "selectedPerkIds": [
          8369,
          8134,
          8143,
          8304,
          8345,
          8347,
          5008,
          5008,
          5001
        ],
        "score": 0,
        "type": ""
      }
    ]
  },
  {
    "index": 109,
    "id": "950",
    "version": "14.5.1",
    "officialVersion": "14.5.1",
    "pickCount": 28,
    "winRate": "39.29%",
    "timestamp": 1709755984766,
    "alias": "Naafiri",
    "name": "Naafiri",
    "position": "jungle",
    "skills": [
      "Q",
      "E",
      "W"
    ],
    "spells": null,
    "itemBuilds": [
      {
        "title": "[u.gg] Naafiri @ jungle, 14.5.1",
        "associatedMaps": [
          11,
          12
        ],
        "associatedChampions": [
          950
        ],
        "blocks": [
          {
            "type": "Starting Items, pick count 17, win 52.94%, Q \u003e E \u003e W",
            "items": [
              {
                "id": "1101",
                "count": 1
              },
              {
                "id": "2003",
                "count": 1
              }
            ]
          },
          {
            "type": "Mythic \u0026 Core Items, pick count 2, win 100.00%, Q \u003e E \u003e W",
            "items": [
              {
                "id": "6698",
                "count": 1
              },
              {
                "id": "6692",
                "count": 1
              },
              {
                "id": "3158",
                "count": 1
              }
            ]
          },
          {
            "type": "Fourth Item Options, Q \u003e E \u003e W",
            "items": [
              {
                "id": "6694",
                "count": 1
              },
              {
                "id": "3814",
                "count": 1
              }
            ]
          },
          {
            "type": "Fifth Item Options, Q \u003e E \u003e W",
            "items": [
              {
                "id": "3814",
                "count": 1
              },
              {
                "id": "6699",
                "count": 1
              },
              {
                "id": "6696",
                "count": 1
              }
            ]
          },
          {
            "type": "Sixth Item Options, Q \u003e E \u003e W",
            "items": [
              {
                "id": "6701",
                "count": 1
              },
              {
                "id": "6697",
                "count": 1
              }
            ]
          }
        ],
        "map": "any",
        "mode": "any",
        "preferredItemSlots": null,
        "sortrank": 1,
        "startedFrom": "blank",
        "type": "custom"
      }
    ],
    "runes": [
      {
        "alias": "Naafiri",
        "name": "[u.gg] Naafiri @ jungle, win 100.00%, pick 1",
        "position": "jungle",
        "pickCount": 1,
        "winRate": "100.00%",
        "primaryStyleId": 8100,
        "subStyleId": 8300,
        "selectedPerkIds": [
          8128,
          8135,
          8138,
          8143,
          8304,
          8347,
          5005,
          5008,
          5001
        ],
        "score": 0,
        "type": ""
      }
    ]
  },
  {
    "index": 109,
    "id": "950",
    "version": "14.5.1",
    "officialVersion": "14.5.1",
    "pickCount": 2,
    "winRate": "50.00%",
    "timestamp": 1709755984766,
    "alias": "Naafiri",
    "name": "Naafiri",
    "position": "supp",
    "skills": [
      "Q",
      "E",
      "W"
    ],
    "spells": null,
    "itemBuilds": [
      {
        "title": "[u.gg] Naafiri @ supp, 14.5.1",
        "associatedMaps": [
          11,
          12
        ],
        "associatedChampions": [
          950
        ],
        "blocks": [
          {
            "type": "Starting Items, pick count 2, win 50.00%, Q \u003e E \u003e W",
            "items": [
              {
                "id": "2003",
                "count": 1
              },
              {
                "id": "2003",
                "count": 1
              },
              {
                "id": "3865",
                "count": 1
              }
            ]
          },
          {
            "type": "Mythic \u0026 Core Items, pick count 1, win 100.00%, Q \u003e E \u003e W",
            "items": [
              {
                "id": "6692",
                "count": 1
              },
              {
                "id": "3047",
                "count": 1
              },
              {
                "id": "3877",
                "count": 1
              }
            ]
          },
          {
            "type": "Fourth Item Options, Q \u003e E \u003e W",
            "items": [
              {
                "id": "6694",
                "count": 1
              }
            ]
          },
          {
            "type": "Fifth Item Options, Q \u003e E \u003e W",
            "items": [
              {
                "id": "6698",
                "count": 1
              }
            ]
          },
          {
            "type": "Sixth Item Options, Q \u003e E \u003e W",
            "items": null
          }
        ],
        "map": "any",
        "mode": "any",
        "preferredItemSlots": null,
        "sortrank": 1,
        "startedFrom": "blank",
        "type": "custom"
      }
    ],
    "runes": [
      {
        "alias": "Naafiri",
        "name": "[u.gg] Naafiri @ supp, win 100.00%, pick 1",
        "position": "supp",
        "pickCount": 1,
        "winRate": "100.00%",
        "primaryStyleId": 8100,
        "subStyleId": 8000,
        "selectedPerkIds": [
          8112,
          8009,
          8014,
          8106,
          8138,
          8143,
          5008,
          5008,
          5001
        ],
        "score": 0,
        "type": ""
      }
    ]
  },
  {
    "index": 109,
    "id": "950",
    "version": "14.5.1",
    "officialVersion": "14.5.1",
    "pickCount": 1,
    "winRate": "100.00%",
    "timestamp": 1709755984766,
    "alias": "Naafiri",
    "name": "Naafiri",
    "position": "adc",
    "skills": [
      "Q",
      "E",
      "W"
    ],
    "spells": null,
    "itemBuilds": [
      {
        "title": "[u.gg] Naafiri @ adc, 14.5.1",
        "associatedMaps": [
          11,
          12
        ],
        "associatedChampions": [
          950
        ],
        "blocks": [
          {
            "type": "Starting Items, pick count 1, win 100.00%, Q \u003e E \u003e W",
            "items": [
              {
                "id": "1054",
                "count": 1
              },
              {
                "id": "2003",
                "count": 1
              }
            ]
          },
          {
            "type": "Mythic \u0026 Core Items, pick count 1, win 100.00%, Q \u003e E \u003e W",
            "items": [
              {
                "id": "6698",
                "count": 1
              },
              {
                "id": "3158",
                "count": 1
              },
              {
                "id": "6692",
                "count": 1
              }
            ]
          },
          {
            "type": "Fourth Item Options, Q \u003e E \u003e W",
            "items": [
              {
                "id": "3814",
                "count": 1
              }
            ]
          },
          {
            "type": "Fifth Item Options, Q \u003e E \u003e W",
            "items": [
              {
                "id": "6701",
                "count": 1
              }
            ]
          },
          {
            "type": "Sixth Item Options, Q \u003e E \u003e W",
            "items": [
              {
                "id": "6697",
                "count": 1
              }
            ]
          }
        ],
        "map": "any",
        "mode": "any",
        "preferredItemSlots": null,
        "sortrank": 1,
        "startedFrom": "blank",
        "type": "custom"
      }
    ],
    "runes": [
      {
        "alias": "Naafiri",
        "name": "[u.gg] Naafiri @ adc, win 100.00%, pick 1",
        "position": "adc",
        "pickCount": 1,
        "winRate": "100.00%",
        "primaryStyleId": 8300,
        "subStyleId": 8100,
        "selectedPerkIds": [
          8369,
          8135,
          8143,
          8304,
          8345,
          8347,
          5008,
          5008,
          5001
        ],
        "score": 0,
        "type": ""
      }
    ]
  }
]