{
    "associatedChampions": [
        "56"
    ],
    "associatedMaps": [
        11,
        12
    ],
    "blocks": [
        {
            "hideIfSummonerSpell": "",
            "items": [
                {
                    "id": "1102",
                    "count": 1
                },
                {
                    "id": "2003",
                    "count": 1
                },
                {
                    "id": "3073",
                    "count": 1
                }
            ],
            "showIfSummonerSpell": "",
            "type": "Starting items"
        },
        {
            "hideIfSummonerSpell": "",
            "items": [
                {
                    "id": "3073",
                    "count": 1
                },
                {
                    "id": "3047",
                    "count": 1
                },
                {
                    "id": "6631",
                    "count": 1
                },
                {
                    "id": "6696",
                    "count": 1
                },
                {
                    "id": "3026",
                    "count": 1
                },
                {
                    "id": "6333",
                    "count": 1
                }
            ],
            "showIfSummonerSpell": "",
            "type": "Core items"
        },
        {
            "hideIfSummonerSpell": "",
            "items": [
                {
                    "id": "3814",
                    "count": 1
                },
                {
                    "id": "3153",
                    "count": 1
                },
                {
                    "id": "3071",
                    "count": 1
                }
            ],
            "showIfSummonerSpell": "",
            "type": "Alternative items"
        }
    ],
    "map": "HA",
    "mode": "any",
    "preferredItemSlots": [],
    "sortrank": 6,
    "startedFrom": "blank",
    "title": "RunitemsBuild - Nocturne",
    "type": "global",
    "uid": "Runeitems"
}