[
  {
    "index": 155,
    "id": "78",
    "version": "14.3.1",
    "officialVersion": "14.3.1",
    "pickCount": 15674,
    "winRate": "51.95%",
    "timestamp": 1708287146556,
    "alias": "Poppy",
    "name": "Poppy",
    "position": "top",
    "skills": [
      "Q",
      "E",
      "W"
    ],
    "spells": null,
    "itemBuilds": [
      {
        "title": "[u.gg] Poppy @ top, 14.3.1",
        "associatedMaps": [
          11,
          12
        ],
        "associatedChampions": [
          78
        ],
        "blocks": [
          {
            "type": "Starting Items, pick count 5802, win 52.36%, Q \u003e E \u003e W",
            "items": [
              {
                "id": "1054",
                "count": 1
              },
              {
                "id": "2003",
                "count": 1
              }
            ]
          },
          {
            "type": "Mythic \u0026 Core Items, pick count 324, win 61.42%, Q \u003e E \u003e W",
            "items": [
              {
                "id": "3047",
                "count": 1
              },
              {
                "id": "3068",
                "count": 1
              },
              {
                "id": "3110",
                "count": 1
              }
            ]
          },
          {
            "type": "Fourth Item Options, Q \u003e E \u003e W",
            "items": [
              {
                "id": "2504",
                "count": 1
              },
              {
                "id": "3075",
                "count": 1
              }
            ]
          },
          {
            "type": "Fifth Item Options, Q \u003e E \u003e W",
            "items": [
              {
                "id": "3075",
                "count": 1
              },
              {
                "id": "2502",
                "count": 1
              },
              {
                "id": "6665",
                "count": 1
              }
            ]
          },
          {
            "type": "Sixth Item Options, Q \u003e E \u003e W",
            "items": [
              {
                "id": "2502",
                "count": 1
              },
              {
                "id": "3075",
                "count": 1
              },
              {
                "id": "6665",
                "count": 1
              }
            ]
          }
        ],
        "map": "any",
        "mode": "any",
        "preferredItemSlots": null,
        "sortrank": 1,
        "startedFrom": "blank",
        "type": "custom"
      }
    ],
    "runes": [
      {
        "alias": "Poppy",
        "name": "[u.gg] Poppy @ top, win 53.57%, pick 1303",
        "position": "top",
        "pickCount": 1303,
        "winRate": "53.57%",
        "primaryStyleId": 8400,
        "subStyleId": 8300,
        "selectedPerkIds": [
          8437,
          8345,
          8352,
          8401,
          8444,
          8453,
          5008,
          5008,
          5011
        ],
        "score": 0,
        "type": ""
      }
    ]
  },
  {
    "index": 155,
    "id": "78",
    "version": "14.3.1",
    "officialVersion": "14.3.1",
    "pickCount": 12966,
    "winRate": "48.90%",
    "timestamp": 1708287146556,
    "alias": "Poppy",
    "name": "Poppy",
    "position": "jungle",
    "skills": [
      "Q",
      "E",
      "W"
    ],
    "spells": null,
    "itemBuilds": [
      {
        "title": "[u.gg] Poppy @ jungle, 14.3.1",
        "associatedMaps": [
          11,
          12
        ],
        "associatedChampions": [
          78
        ],
        "blocks": [
          {
            "type": "Starting Items, pick count 8047, win 49.04%, Q \u003e E \u003e W",
            "items": [
              {
                "id": "1102",
                "count": 1
              },
              {
                "id": "2003",
                "count": 1
              }
            ]
          },
          {
            "type": "Mythic \u0026 Core Items, pick count 563, win 58.26%, Q \u003e E \u003e W",
            "items": [
              {
                "id": "6610",
                "count": 1
              },
              {
                "id": "3111",
                "count": 1
              },
              {
                "id": "3742",
                "count": 1
              }
            ]
          },
          {
            "type": "Fourth Item Options, Q \u003e E \u003e W",
            "items": [
              {
                "id": "2504",
                "count": 1
              },
              {
                "id": "3075",
                "count": 1
              }
            ]
          },
          {
            "type": "Fifth Item Options, Q \u003e E \u003e W",
            "items": [
              {
                "id": "3143",
                "count": 1
              },
              {
                "id": "3075",
                "count": 1
              },
              {
                "id": "3110",
                "count": 1
              }
            ]
          },
          {
            "type": "Sixth Item Options, Q \u003e E \u003e W",
            "items": [
              {
                "id": "3143",
                "count": 1
              },
              {
                "id": "2502",
                "count": 1
              },
              {
                "id": "2504",
                "count": 1
              }
            ]
          }
        ],
        "map": "any",
        "mode": "any",
        "preferredItemSlots": null,
        "sortrank": 1,
        "startedFrom": "blank",
        "type": "custom"
      }
    ],
    "runes": [
      {
        "alias": "Poppy",
        "name": "[u.gg] Poppy @ jungle, win 51.66%, pick 2617",
        "position": "jungle",
        "pickCount": 2617,
        "winRate": "51.66%",
        "primaryStyleId": 8100,
        "subStyleId": 8200,
        "selectedPerkIds": [
          8128,
          8105,
          8126,
          8138,
          8232,
          8234,
          5008,
          5008,
          5001
        ],
        "score": 0,
        "type": ""
      }
    ]
  },
  {
    "index": 155,
    "id": "78",
    "version": "14.3.1",
    "officialVersion": "14.3.1",
    "pickCount": 2886,
    "winRate": "53.71%",
    "timestamp": 1708287146556,
    "alias": "Poppy",
    "name": "Poppy",
    "position": "supp",
    "skills": [
      "Q",
      "E",
      "W"
    ],
    "spells": null,
    "itemBuilds": [
      {
        "title": "[u.gg] Poppy @ supp, 14.3.1",
        "associatedMaps": [
          11,
          12
        ],
        "associatedChampions": [
          78
        ],
        "blocks": [
          {
            "type": "Starting Items, pick count 2702, win 53.44%, Q \u003e E \u003e W",
            "items": [
              {
                "id": "2003",
                "count": 1
              },
              {
                "id": "2003",
                "count": 1
              },
              {
                "id": "3865",
                "count": 1
              }
            ]
          },
          {
            "type": "Mythic \u0026 Core Items, pick count 116, win 65.52%, Q \u003e E \u003e W",
            "items": [
              {
                "id": "3877",
                "count": 1
              },
              {
                "id": "3009",
                "count": 1
              },
              {
                "id": "3002",
                "count": 1
              }
            ]
          },
          {
            "type": "Fourth Item Options, Q \u003e E \u003e W",
            "items": [
              {
                "id": "2504",
                "count": 1
              },
              {
                "id": "3742",
                "count": 1
              }
            ]
          },
          {
            "type": "Fifth Item Options, Q \u003e E \u003e W",
            "items": [
              {
                "id": "3110",
                "count": 1
              },
              {
                "id": "3075",
                "count": 1
              },
              {
                "id": "2504",
                "count": 1
              }
            ]
          },
          {
            "type": "Sixth Item Options, Q \u003e E \u003e W",
            "items": [
              {
                "id": "2504",
                "count": 1
              },
              {
                "id": "4643",
                "count": 1
              },
              {
                "id": "3110",
                "count": 1
              }
            ]
          }
        ],
        "map": "any",
        "mode": "any",
        "preferredItemSlots": null,
        "sortrank": 1,
        "startedFrom": "blank",
        "type": "custom"
      }
    ],
    "runes": [
      {
        "alias": "Poppy",
        "name": "[u.gg] Poppy @ supp, win 54.34%, pick 692",
        "position": "supp",
        "pickCount": 692,
        "winRate": "54.34%",
        "primaryStyleId": 8400,
        "subStyleId": 8300,
        "selectedPerkIds": [
          8439,
          8242,
          8306,
          8347,
          8463,
          8473,
          5008,
          5008,
          5011
        ],
        "score": 0,
        "type": ""
      }
    ]
  },
  {
    "index": 155,
    "id": "78",
    "version": "14.3.1",
    "officialVersion": "14.3.1",
    "pickCount": 380,
    "winRate": "51.58%",
    "timestamp": 1708287146556,
    "alias": "Poppy",
    "name": "Poppy",
    "position": "mid",
    "skills": [
      "Q",
      "W",
      "E"
    ],
    "spells": null,
    "itemBuilds": [
      {
        "title": "[u.gg] Poppy @ mid, 14.3.1",
        "associatedMaps": [
          11,
          12
        ],
        "associatedChampions": [
          78
        ],
        "blocks": [
          {
            "type": "Starting Items, pick count 171, win 52.63%, Q \u003e W \u003e E",
            "items": [
              {
                "id": "2033",
                "count": 1
              }
            ]
          },
          {
            "type": "Mythic \u0026 Core Items, pick count 9, win 88.89%, Q \u003e W \u003e E",
            "items": [
              {
                "id": "3047",
                "count": 1
              },
              {
                "id": "3068",
                "count": 1
              },
              {
                "id": "6662",
                "count": 1
              }
            ]
          },
          {
            "type": "Fourth Item Options, Q \u003e W \u003e E",
            "items": [
              {
                "id": "3075",
                "count": 1
              },
              {
                "id": "2502",
                "count": 1
              }
            ]
          },
          {
            "type": "Fifth Item Options, Q \u003e W \u003e E",
            "items": [
              {
                "id": "3075",
                "count": 1
              },
              {
                "id": "3071",
                "count": 1
              },
              {
                "id": "2504",
                "count": 1
              }
            ]
          },
          {
            "type": "Sixth Item Options, Q \u003e W \u003e E",
            "items": [
              {
                "id": "8001",
                "count": 1
              },
              {
                "id": "6665",
                "count": 1
              },
              {
                "id": "3142",
                "count": 1
              }
            ]
          }
        ],
        "map": "any",
        "mode": "any",
        "preferredItemSlots": null,
        "sortrank": 1,
        "startedFrom": "blank",
        "type": "custom"
      }
    ],
    "runes": [
      {
        "alias": "Poppy",
        "name": "[u.gg] Poppy @ mid, win 100.00%, pick 4",
        "position": "mid",
        "pickCount": 4,
        "winRate": "100.00%",
        "primaryStyleId": 8400,
        "subStyleId": 8200,
        "selectedPerkIds": [
          8437,
          8226,
          8237,
          8444,
          8446,
          8453,
          5008,
          5008,
          5011
        ],
        "score": 0,
        "type": ""
      }
    ]
  },
  {
    "index": 155,
    "id": "78",
    "version": "14.3.1",
    "officialVersion": "14.3.1",
    "pickCount": 51,
    "winRate": "54.90%",
    "timestamp": 1708287146556,
    "alias": "Poppy",
    "name": "Poppy",
    "position": "adc",
    "skills": [
      "Q",
      "E",
      "W"
    ],
    "spells": null,
    "itemBuilds": [
      {
        "title": "[u.gg] Poppy @ adc, 14.3.1",
        "associatedMaps": [
          11,
          12
        ],
        "associatedChampions": [
          78
        ],
        "blocks": [
          {
            "type": "Starting Items, pick count 6, win 66.67%, Q \u003e E \u003e W",
            "items": [
              {
                "id": "2033",
                "count": 1
              }
            ]
          },
          {
            "type": "Mythic \u0026 Core Items, pick count 3, win 100.00%, Q \u003e E \u003e W",
            "items": [
              {
                "id": "3068",
                "count": 1
              },
              {
                "id": "3047",
                "count": 1
              },
              {
                "id": "3075",
                "count": 1
              }
            ]
          },
          {
            "type": "Fourth Item Options, Q \u003e E \u003e W",
            "items": [
              {
                "id": "2504",
                "count": 1
              },
              {
                "id": "3190",
                "count": 1
              }
            ]
          },
          {
            "type": "Fifth Item Options, Q \u003e E \u003e W",
            "items": [
              {
                "id": "6694",
                "count": 1
              },
              {
                "id": "3142",
                "count": 1
              },
              {
                "id": "3033",
                "count": 1
              }
            ]
          },
          {
            "type": "Sixth Item Options, Q \u003e E \u003e W",
            "items": [
              {
                "id": "6701",
                "count": 1
              },
              {
                "id": "6610",
                "count": 1
              },
              {
                "id": "2504",
                "count": 1
              }
            ]
          }
        ],
        "map": "any",
        "mode": "any",
        "preferredItemSlots": null,
        "sortrank": 1,
        "startedFrom": "blank",
        "type": "custom"
      }
    ],
    "runes": [
      {
        "alias": "Poppy",
        "name": "[u.gg] Poppy @ adc, win 100.00%, pick 3",
        "position": "adc",
        "pickCount": 3,
        "winRate": "100.00%",
        "primaryStyleId": 8400,
        "subStyleId": 8300,
        "selectedPerkIds": [
          8437,
          8345,
          8352,
          8401,
          8453,
          8473,
          5008,
          5008,
          5001
        ],
        "score": 0,
        "type": ""
      }
    ]
  }
]