{
    "associatedChampions": [
        "133"
    ],
    "associatedMaps": [
        11,
        12
    ],
    "blocks": [
        {
            "hideIfSummonerSpell": "",
            "items": [
                {
                    "id": "1055",
                    "count": 1
                },
                {
                    "id": "2003",
                    "count": 1
                },
                {
                    "id": "3006",
                    "count": 1
                }
            ],
            "showIfSummonerSpell": "",
            "type": "Starting items"
        },
        {
            "hideIfSummonerSpell": "",
            "items": [
                {
                    "id": "3006",
                    "count": 1
                },
                {
                    "id": "3087",
                    "count": 1
                },
                {
                    "id": "6672",
                    "count": 1
                },
                {
                    "id": "6676",
                    "count": 1
                },
                {
                    "id": "3814",
                    "count": 1
                },
                {
                    "id": "3036",
                    "count": 1
                }
            ],
            "showIfSummonerSpell": "",
            "type": "Core items"
        },
        {
            "hideIfSummonerSpell": "",
            "items": [
                {
                    "id": "6699",
                    "count": 1
                },
                {
                    "id": "3156",
                    "count": 1
                }
            ],
            "showIfSummonerSpell": "",
            "type": "Alternative items"
        }
    ],
    "map": "HA",
    "mode": "any",
    "preferredItemSlots": [],
    "sortrank": 6,
    "startedFrom": "blank",
    "title": "RunitemsBuild - Quinn",
    "type": "global",
    "uid": "Runeitems"
}