[
  {
    "index": 12,
    "id": "44",
    "version": "14.5.1",
    "officialVersion": "14.5.1",
    "pickCount": 297,
    "winRate": "50.84%",
    "timestamp": 1709755984766,
    "alias": "Taric",
    "name": "Taric",
    "position": "supp",
    "skills": [
      "E",
      "W",
      "Q"
    ],
    "spells": null,
    "itemBuilds": [
      {
        "title": "[u.gg] Taric @ supp, 14.5.1",
        "associatedMaps": [
          11,
          12
        ],
        "associatedChampions": [
          44
        ],
        "blocks": [
          {
            "type": "Starting Items, pick count 294, win 51.02%, E \u003e W \u003e Q",
            "items": [
              {
                "id": "2003",
                "count": 1
              },
              {
                "id": "2003",
                "count": 1
              },
              {
                "id": "3865",
                "count": 1
              }
            ]
          },
          {
            "type": "Mythic \u0026 Core Items, pick count 3, win 100.00%, E \u003e W \u003e Q",
            "items": [
              {
                "id": "3158",
                "count": 1
              },
              {
                "id": "3002",
                "count": 1
              },
              {
                "id": "3876",
                "count": 1
              }
            ]
          },
          {
            "type": "Fourth Item Options, E \u003e W \u003e Q",
            "items": [
              {
                "id": "3109",
                "count": 1
              },
              {
                "id": "3050",
                "count": 1
              }
            ]
          },
          {
            "type": "Fifth Item Options, E \u003e W \u003e Q",
            "items": [
              {
                "id": "3119",
                "count": 1
              },
              {
                "id": "2504",
                "count": 1
              },
              {
                "id": "4643",
                "count": 1
              }
            ]
          },
          {
            "type": "Sixth Item Options, E \u003e W \u003e Q",
            "items": [
              {
                "id": "3190",
                "count": 1
              },
              {
                "id": "3107",
                "count": 1
              }
            ]
          }
        ],
        "map": "any",
        "mode": "any",
        "preferredItemSlots": null,
        "sortrank": 1,
        "startedFrom": "blank",
        "type": "custom"
      }
    ],
    "runes": [
      {
        "alias": "Taric",
        "name": "[u.gg] Taric @ supp, win 85.71%, pick 7",
        "position": "supp",
        "pickCount": 7,
        "winRate": "85.71%",
        "primaryStyleId": 8300,
        "subStyleId": 8000,
        "selectedPerkIds": [
          8351,
          8009,
          8306,
          8345,
          8347,
          9105,
          5005,
          5008,
          5013
        ],
        "score": 0,
        "type": ""
      }
    ]
  },
  {
    "index": 12,
    "id": "44",
    "version": "14.5.1",
    "officialVersion": "14.5.1",
    "pickCount": 5,
    "winRate": "80.00%",
    "timestamp": 1709755984766,
    "alias": "Taric",
    "name": "Taric",
    "position": "top",
    "skills": [
      "W",
      "Q",
      "E"
    ],
    "spells": null,
    "itemBuilds": [
      {
        "title": "[u.gg] Taric @ top, 14.5.1",
        "associatedMaps": [
          11,
          12
        ],
        "associatedChampions": [
          44
        ],
        "blocks": [
          {
            "type": "Starting Items, pick count 1, win 100.00%, W \u003e Q \u003e E",
            "items": [
              {
                "id": "2003",
                "count": 1
              },
              {
                "id": "2003",
                "count": 1
              },
              {
                "id": "3865",
                "count": 1
              }
            ]
          },
          {
            "type": "Mythic \u0026 Core Items, pick count 1, win 100.00%, W \u003e Q \u003e E",
            "items": [
              {
                "id": "6662",
                "count": 1
              },
              {
                "id": "3047",
                "count": 1
              },
              {
                "id": "3065",
                "count": 1
              }
            ]
          },
          {
            "type": "Fourth Item Options, W \u003e Q \u003e E",
            "items": [
              {
                "id": "3504",
                "count": 1
              }
            ]
          },
          {
            "type": "Fifth Item Options, W \u003e Q \u003e E",
            "items": null
          },
          {
            "type": "Sixth Item Options, W \u003e Q \u003e E",
            "items": null
          }
        ],
        "map": "any",
        "mode": "any",
        "preferredItemSlots": null,
        "sortrank": 1,
        "startedFrom": "blank",
        "type": "custom"
      }
    ],
    "runes": [
      {
        "alias": "Taric",
        "name": "[u.gg] Taric @ top, win 100.00%, pick 1",
        "position": "top",
        "pickCount": 1,
        "winRate": "100.00%",
        "primaryStyleId": 8400,
        "subStyleId": 8100,
        "selectedPerkIds": [
          8465,
          8106,
          8126,
          8429,
          8453,
          8463,
          5007,
          5010,
          5001
        ],
        "score": 0,
        "type": ""
      }
    ]
  },
  {
    "index": 12,
    "id": "44",
    "version": "14.5.1",
    "officialVersion": "14.5.1",
    "pickCount": 5,
    "winRate": "60.00%",
    "timestamp": 1709755984766,
    "alias": "Taric",
    "name": "Taric",
    "position": "adc",
    "skills": [
      "E",
      "W",
      "Q"
    ],
    "spells": null,
    "itemBuilds": [
      {
        "title": "[u.gg] Taric @ adc, 14.5.1",
        "associatedMaps": [
          11,
          12
        ],
        "associatedChampions": [
          44
        ],
        "blocks": [
          {
            "type": "Starting Items, pick count 5, win 60.00%, E \u003e W \u003e Q",
            "items": [
              {
                "id": "1054",
                "count": 1
              },
              {
                "id": "2003",
                "count": 1
              }
            ]
          },
          {
            "type": "Mythic \u0026 Core Items, pick count 1, win 100.00%, E \u003e W \u003e Q",
            "items": [
              {
                "id": "6662",
                "count": 1
              },
              {
                "id": "3047",
                "count": 1
              },
              {
                "id": "3119",
                "count": 1
              }
            ]
          },
          {
            "type": "Fourth Item Options, E \u003e W \u003e Q",
            "items": [
              {
                "id": "3143",
                "count": 1
              }
            ]
          },
          {
            "type": "Fifth Item Options, E \u003e W \u003e Q",
            "items": null
          },
          {
            "type": "Sixth Item Options, E \u003e W \u003e Q",
            "items": null
          }
        ],
        "map": "any",
        "mode": "any",
        "preferredItemSlots": null,
        "sortrank": 1,
        "startedFrom": "blank",
        "type": "custom"
      }
    ],
    "runes": [
      {
        "alias": "Taric",
        "name": "[u.gg] Taric @ adc, win 100.00%, pick 1",
        "position": "adc",
        "pickCount": 1,
        "winRate": "100.00%",
        "primaryStyleId": 8400,
        "subStyleId": 8300,
        "selectedPerkIds": [
          8465,
          8304,
          8347,
          8401,
          8444,
          8453,
          5005,
          5001,
          5011
        ],
        "score": 0,
        "type": ""
      }
    ]
  },
  {
    "index": 12,
    "id": "44",
    "version": "14.5.1",
    "officialVersion": "14.5.1",
    "pickCount": 4,
    "winRate": "50.00%",
    "timestamp": 1709755984766,
    "alias": "Taric",
    "name": "Taric",
    "position": "jungle",
    "skills": [
      "E",
      "W",
      "Q"
    ],
    "spells": null,
    "itemBuilds": [
      {
        "title": "[u.gg] Taric @ jungle, 14.5.1",
        "associatedMaps": [
          11,
          12
        ],
        "associatedChampions": [
          44
        ],
        "blocks": [
          {
            "type": "Starting Items, pick count 3, win 66.67%, E \u003e W \u003e Q",
            "items": [
              {
                "id": "1102",
                "count": 1
              }
            ]
          },
          {
            "type": "Mythic \u0026 Core Items, pick count 1, win 100.00%, E \u003e W \u003e Q",
            "items": [
              {
                "id": "6662",
                "count": 1
              },
              {
                "id": "3158",
                "count": 1
              },
              {
                "id": "3119",
                "count": 1
              }
            ]
          },
          {
            "type": "Fourth Item Options, E \u003e W \u003e Q",
            "items": null
          },
          {
            "type": "Fifth Item Options, E \u003e W \u003e Q",
            "items": null
          },
          {
            "type": "Sixth Item Options, E \u003e W \u003e Q",
            "items": null
          }
        ],
        "map": "any",
        "mode": "any",
        "preferredItemSlots": null,
        "sortrank": 1,
        "startedFrom": "blank",
        "type": "custom"
      }
    ],
    "runes": [
      {
        "alias": "Taric",
        "name": "[u.gg] Taric @ jungle, win 100.00%, pick 2",
        "position": "jungle",
        "pickCount": 2,
        "winRate": "100.00%",
        "primaryStyleId": 8400,
        "subStyleId": 8300,
        "selectedPerkIds": [
          8465,
          8304,
          8401,
          8410,
          8429,
          8453,
          5005,
          5001,
          5011
        ],
        "score": 0,
        "type": ""
      }
    ]
  },
  {
    "index": 12,
    "id": "44",
    "version": "14.5.1",
    "officialVersion": "14.5.1",
    "pickCount": 2,
    "winRate": "0.00%",
    "timestamp": 1709755984766,
    "alias": "Taric",
    "name": "Taric",
    "position": "mid",
    "skills": [
      "E",
      "Q",
      "W"
    ],
    "spells": null,
    "itemBuilds": [
      {
        "title": "[u.gg] Taric @ mid, 14.5.1",
        "associatedMaps": [
          11,
          12
        ],
        "associatedChampions": [
          44
        ],
        "blocks": [
          {
            "type": "Starting Items, pick count 1, win 0.00%, E \u003e Q \u003e W",
            "items": [
              {
                "id": "2003",
                "count": 1
              },
              {
                "id": "2003",
                "count": 1
              },
              {
                "id": "3865",
                "count": 1
              }
            ]
          },
          {
            "type": "Mythic \u0026 Core Items, pick count 1, win 0.00%, E \u003e Q \u003e W",
            "items": [
              {
                "id": "3876",
                "count": 1
              },
              {
                "id": "3109",
                "count": 1
              },
              {
                "id": "3504",
                "count": 1
              }
            ]
          },
          {
            "type": "Fourth Item Options, E \u003e Q \u003e W",
            "items": null
          },
          {
            "type": "Fifth Item Options, E \u003e Q \u003e W",
            "items": null
          },
          {
            "type": "Sixth Item Options, E \u003e Q \u003e W",
            "items": null
          }
        ],
        "map": "any",
        "mode": "any",
        "preferredItemSlots": null,
        "sortrank": 1,
        "startedFrom": "blank",
        "type": "custom"
      }
    ],
    "runes": [
      {
        "alias": "Taric",
        "name": "[u.gg] Taric @ mid, win 0.00%, pick 1",
        "position": "mid",
        "pickCount": 1,
        "winRate": "0.00%",
        "primaryStyleId": 8400,
        "subStyleId": 8100,
        "selectedPerkIds": [
          8465,
          8106,
          8126,
          8429,
          8453,
          8463,
          5007,
          5010,
          5001
        ],
        "score": 0,
        "type": ""
      }
    ]
  }
]